ChangeLog
LICENSE
MANIFEST.in
README.md
README.rst
example.py
setup.py
QueryableList/Base.py
QueryableList/Builder.py
QueryableList/__init__.py
QueryableList/constants.py
QueryableList.egg-info/PKG-INFO
QueryableList.egg-info/SOURCES.txt
QueryableList.egg-info/dependency_links.txt
QueryableList.egg-info/top_level.txt
doc/QueryableList.Base.html
doc/QueryableList.Builder.html
doc/QueryableList.constants.html
doc/QueryableList.html
doc/index.html
tests/runTests.py
tests/QueryableListTests/test_BasicFiltering.py
tests/QueryableListTests/test_Operations.py
tests/QueryableListTests/test_Performance.py
tests/QueryableListTests/test_QueryableListTypes.py
tests/QueryableListTests/test_Sorting.py
tests/QueryableListTests/test_SpecialOps.py
tests/QueryableListTests/tutils.py