Metadata-Version: 1.1
Name: QueryableList
Version: 3.1.0
Summary: Python module to add support for ORM-style filtering to any list of items
Home-page: https://github.com/kata198/QueryableList
Author: Tim Savannah
Author-email: kata198@gmail.com
License: LGPLv2
Keywords: queryablelist,query,list,filter,objects,eq,ne,lt,gt,equals,not,compare,comprehension,orm,queryable,django,flask,indexedredis,contains,icontains
Platform: UNKNOWN
Classifier: Development Status :: 5 - Production/Stable
Classifier: Programming Language :: Python
Classifier: License :: OSI Approved :: GNU Lesser General Public License v2 (LGPLv2)
Classifier: Programming Language :: Python :: 2
Classifier: Programming Language :: Python :: 2
Classifier: Programming Language :: Python :: 2.7
Classifier: Programming Language :: Python :: 3
Classifier: Programming Language :: Python :: 3.3
Classifier: Programming Language :: Python :: 3.4
Classifier: Programming Language :: Python :: 3.5
Classifier: Programming Language :: Python :: 3.6
Classifier: Topic :: Software Development :: Libraries :: Python Modules
